setup.cfg
setup.py
gooeydist/__init__.py
gooeydist/gooey.py
gooeydist.egg-info/PKG-INFO
gooeydist.egg-info/SOURCES.txt
gooeydist.egg-info/dependency_links.txt
gooeydist.egg-info/top_level.txt
gooeydist/grammar/__init__.py
gooeydist/grammar/attributes.py
gooeydist/grammar/statements.py
gooeydist/interpreter/__init__.py
gooeydist/interpreter/actionbuttons.py
gooeydist/interpreter/interpreter.py
gooeydist/interpreter/matrix.py
gooeydist/pypeg2/__init__.py
gooeydist/pypeg2/xmlast.py
gooeydist/pypeg2/test/__init__.py
gooeydist/pypeg2/test/test_pypeg2.py
gooeydist/pypeg2/test/test_xmlast.py