Metadata-Version: 1.1
Name: gooeydist
Version: 0.2
Summary: Gooey Language
Home-page: https://github.com/GooeyComps/gooey-dist
Author: Gooey Comps
Author-email: harrise@carleton.edu
License: UNKNOWN
Download-URL: https://github.com/GooeyComps/gooey-dist/tarball/0.2
Keywords: gui
Platform: UNKNOWN
